[
  {
    "id": "210297191",
    "title": "Audi e-tron Individual/360/s-line/matrix",
    "price": "749 000 Kč",
    "details": "2022, 27 147 km , Elektro , Automatická  ·  Brno-město  ·  Fair Play Cars, s.r.o.",
    "link": "https://www.sauto.cz/osobni/detail/audi/e-tron/210297191",
    "image": "https://d19-a.sdn.cz/d_19/c_img_qA_B/nCTUX1iX5CFdAHBBmmGaZ8C3/50ca.jpeg?fl=exf|res,360,270,3|jpg,80,,1",
    "found_at": "22.04.2026 13:09"
  },
  {
    "id": "210299978",
    "title": "BMW Řada 1 120i M Sport Virtual Pano LED",
    "price": "619 000 Kč",
    "details": "2023, 75 550 km , Benzín , Automatická  ·  Brno-město  ·  Autocentrum Šerý s.r.o.",
    "link": "https://www.sauto.cz/osobni/detail/bmw/rada-1/210299978",
    "image": "https://d19-a.sdn.cz/d_19/c_img_qA_B/kcHp2YdDtzYqG503Gahy6g/78b3.jpeg?fl=exf|res,360,270,3|jpg,80,,1",
    "found_at": "22.04.2026 18:10"
  },
  {
    "id": "210183077",
    "title": "Mercedes-Benz Třídy E Mercedes-Benz E 200 2020",
    "price": "630 000 Kč",
    "details": "2020, 95 000 km , Benzín , Automatická  ·  Hlavní město Praha  ·  Boss Auto CZ",
    "link": "https://www.sauto.cz/osobni/detail/mercedes-benz/tridy-e/210183077",
    "image": "https://d19-a.sdn.cz/d_19/c_img_qA_A/nCTUX1iX5BWZuTRO6GOQPPR/03d4.jpeg?fl=exf|res,360,270,3|jpg,80,,1",
    "found_at": "22.04.2026 18:10"
  },
  {
    "id": "210299969",
    "title": "Mini Cooper JOHN COOPER WORKS 170 kW",
    "price": "729 900 Kč",
    "details": "2023, 25 280 km , Benzín , Automatická  ·  Hlavní město Praha  ·  AUTO Z DOVOZU",
    "link": "https://www.sauto.cz/osobni/detail/mini/cooper/210299969",
    "image": "https://d19-a.sdn.cz/d_19/c_img_qA_B/nCTUX1iX5BWLrlBB6sGahvy4/a4c8.jpeg?fl=exf|res,360,270,3|jpg,80,,1",
    "found_at": "22.04.2026 18:10"
  }
]