[
  {
    "id": "210021351",
    "title": "Mercedes-Benz CLA AMG 45S, Shooting",
    "price": "304 500 Kč",
    "details": "2020, 86 370 km , Benzín , Automatická  ·  Hlavní město Praha  ·  Soukromý",
    "link": "https://www.sauto.cz/osobni/detail/mercedes-benz/cla/210021351",
    "image": "https://d19-a.sdn.cz/d_19/c_img_p9_A/kcHp2YdDtBM3KVBBwF9K6iW/55e8.jpeg?fl=exf|res,360,270,3|jpg,80,,1",
    "found_at": "07.03.2026 07:47"
  },
  {
    "id": "209768100",
    "title": "Mercedes-Benz GLB 200D 4x4, 7-míst, top stav",
    "price": "750 000 Kč",
    "details": "2022, 80 000 km , Nafta , Automatická  ·  Hlavní město Praha  ·  Soukromý",
    "link": "https://www.sauto.cz/osobni/detail/mercedes-benz/glb/209768100",
    "image": "https://d19-a.sdn.cz/d_19/c_img_p7_A/kOzkBkwYBTCNNSBPm2FismKV/b84c.jpeg?fl=exf|res,360,270,3|jpg,80,,1",
    "found_at": "07.03.2026 07:47"
  },
  {
    "id": "210022764",
    "title": "BMW i3 120Ah/42kW Zár.BMW, Pneu+D,",
    "price": "458 590 Kč",
    "details": "2021, 74 800 km , Elektro , Automatická  ·  Svitavy  ·  Soukromý",
    "link": "https://www.sauto.cz/osobni/detail/bmw/i3/210022764",
    "image": "https://d19-a.sdn.cz/d_19/c_img_p9_A/kcHp2YdDtDgLT0BKsF9irZ2/fecf.jpeg?fl=exf|res,360,270,3|jpg,80,,1",
    "found_at": "07.03.2026 16:27"
  },
  {
    "id": "209764203",
    "title": "Audi A5 Sportsback Sline",
    "price": "590 000 Kč",
    "details": "2021, 64 000 km , Benzín , Automatická  ·  Hlavní město Praha  ·  Soukromý",
    "link": "https://www.sauto.cz/osobni/detail/audi/a5/209764203",
    "image": "https://d19-a.sdn.cz/d_19/c_img_p8_A/kBfrbpoeNCqNsfBH2FuhhOX/9e99.jpeg?fl=exf|res,360,270,3|jpg,80,,1",
    "found_at": "07.03.2026 16:27"
  }
]